selfext/__init__.py
selfext-0.0.0.dist-info/METADATA
selfext-0.0.0.dist-info/RECORD
selfext-0.0.0.dist-info/WHEEL
selfext-0.0.0.dist-info/entry_points.txt
selfext-0.0.0.dist-info/top_level.txt
