Metadata-Version: 2.1
Name: selfext
Version: 0.0.0
Summary: Generate self-extracting script.
Home-page: https://github.com/kazukazuprogram/selfext
Author: kazukazuprogram
Author-email: dbycvil8yiyf7xnlxvh7@yahoo.co.jp
Maintainer: kazukazuprogram
Maintainer-email: dbycvil8yiyf7xnlxvh7@yahoo.co.jp
License: MIT
Platform: UNKNOWN
